copy_paste/__init__.py
copy_paste/coco.py
copy_paste/copy_paste.py
copy_paste/example_coco.ipynb
copy_paste/visualize.py
copy_paste_augmentation-0.1.0.dist-info/LICENSE
copy_paste_augmentation-0.1.0.dist-info/METADATA
copy_paste_augmentation-0.1.0.dist-info/WHEEL
copy_paste_augmentation-0.1.0.dist-info/RECORD
