Metadata-Version: 2.1
Name: copy-paste-augmentation
Version: 0.1.0
Summary: Copy & Paste augmentation
License: MIT
Author: h3dema
Author-email: henrique.duartemoura@imec.be
Requires-Python: >=3.10,<4.0
Classifier: License :: OSI Approved :: MIT License
Classifier: Programming Language :: Python :: 3
Classifier: Programming Language :: Python :: 3.10
Classifier: Programming Language :: Python :: 3.11
Classifier: Programming Language :: Python :: 3.12
Requires-Dist: albumentations (>=1.4.24,<2.0.0)
Requires-Dist: matplotlib (>=3.10.0,<4.0.0)
Requires-Dist: numpy (>=2.2.1,<3.0.0)
Requires-Dist: pycocotools (>=2.0.8,<3.0.0)
Requires-Dist: scikit-image (>=0.25.0,<0.26.0)
